detacache/__init__.py
detacache/coder.py
detacache/decorators.py
detacache/key.py
detacache/core/__init__.py
detacache/core/_coder.py
detacache/core/_decorators.py
detacache/core/_detaBase.py
detacache/core/_helpers.py
detacache/core/_key.py
detacache-0.1.2.dist-info/LICENSE.txt
detacache-0.1.2.dist-info/METADATA
detacache-0.1.2.dist-info/WHEEL
detacache-0.1.2.dist-info/top_level.txt
detacache-0.1.2.dist-info/RECORD
