Metadata-Version: 2.1
Name: detacache
Version: 0.1.2
Summary: Async and Sync Function Decorator to cache function call's to Deta base
Home-page: https://github.com/vidyasagar1432/detacache
Author: vidya sagar
Author-email: svidya051@gmail.com
License: MIT
Keywords: deta,cache,asyncio,deta base cache,fastapi cache,cache api call,cache functions,cache requests
Classifier: Development Status :: 4 - Beta
Classifier: Intended Audience :: Developers
Classifier: License :: OSI Approved :: MIT License
Classifier: Operating System :: OS Independent
Classifier: Programming Language :: Python :: 3
Requires-Python: >=3.6
License-File: LICENSE.txt
Requires-Dist: aiohttp
Requires-Dist: requests
